{
  "bhavya jadwani": "01- 1st",
  "aaditya kalwani": "09- 11th",
  "arun kalwani": "10- 15th",
  "chandani kalwani": "08- 11th",
  "avinash kalwani": "09- 10th",
  "arya maheshwari": "01- 3rd",
  "riya gupta": "01- 9th",
  "mahi": "01- 14th",
  "yashna": "02- 5th",
  "lily cornell": "02- 20th",
  "shalini kalwani": "03- 11th",
  "issy byrne": "03- 15th",
  "nishita jadwani": "04- 12th",
  "tannu dadlani": "05- 17th",
  "aanchal kalwani": "05- 17th",
  "neetu bua": "06- 3rd",
  "yoshi makhija": "06- 7th",
  "04- duma": "06- 21st",
  "jeenisa thapa": "06- 26th",
  "lucia": "06-28th",
  "emilia brasch": "07- 10th",
  "rebecca thomas": "08- 1st",
  "vanshika pithalia": "16/08",
  "malina hawthorne": "30/08",
  "smera nathani": "06/11",
  "angel jadwani": "22/12",
  "princess jadwani": "22/12",
  "maisie morton": "23/12"
}